<?xml version="1.0" encoding="utf-8" ?><dwsync><file name="alert.js" server="ftp.greenwoodcreative.com" local="3545906288" remote="3548942040" Dst="-1" /><file name="button.js" server="ftp.greenwoodcreative.com" local="3545906288" remote="3548942040" Dst="-1" /><file name="alert.min.js" server="ftp.greenwoodcreative.com" local="3545906288" remote="3548942040" Dst="-1" /><file name="button.min.js" server="ftp.greenwoodcreative.com" local="3545906288" remote="3548942040" Dst="-1" /><file name="core.js" server="ftp.greenwoodcreative.com" local="3545906288" remote="3548942040" Dst="-1" /><file name="cover.js" server="ftp.greenwoodcreative.com" local="3545906288" remote="3548942040" Dst="-1" /><file name="core.min.js" server="ftp.greenwoodcreative.com" local="3545906288" remote="3548942040" Dst="-1" /><file name="cover.min.js" server="ftp.greenwoodcreative.com" local="3545906288" remote="3548942040" Dst="-1" /><file name="dropdown.js" server="ftp.greenwoodcreative.com" local="3545906288" remote="3548942040" Dst="-1" /><file name="dropdown.min.js" server="ftp.greenwoodcreative.com" local="3545906288" remote="3548942040" Dst="-1" /><file name="grid.js" server="ftp.greenwoodcreative.com" local="3545906288" remote="3548942040" Dst="-1" /><file name="grid.min.js" server="ftp.greenwoodcreative.com" local="3545906288" remote="3548942040" Dst="-1" /><file name="modal.js" server="ftp.greenwoodcreative.com" local="3545906288" remote="3548942040" Dst="-1" /><file name="modal.min.js" server="ftp.greenwoodcreative.com" local="3545906288" remote="3548942040" Dst="-1" /><file name="nav.min.js" server="ftp.greenwoodcreative.com" local="3545906288" remote="3548942040" Dst="-1" /><file name="offcanvas.js" server="ftp.greenwoodcreative.com" local="3545906288" remote="3548942040" Dst="-1" /><file name="nav.js" server="ftp.greenwoodcreative.com" local="3545906288" remote="3548942040" Dst="-1" /><file name="offcanvas.min.js" server="ftp.greenwoodcreative.com" local="3545906288" remote="3548942040" Dst="-1" /><file name="scrollspy.min.js" server="ftp.greenwoodcreative.com" local="3545906288" remote="3548942040" Dst="-1" /><file name="scrollspy.js" server="ftp.greenwoodcreative.com" local="3545906288" remote="3548942040" Dst="-1" /><file name="smooth-scroll.min.js" server="ftp.greenwoodcreative.com" local="3545906288" remote="3548942040" Dst="-1" /><file name="smooth-scroll.js" server="ftp.greenwoodcreative.com" local="3545906288" remote="3548942040" Dst="-1" /><file name="switcher.js" server="ftp.greenwoodcreative.com" local="3545906288" remote="3548942040" Dst="-1" /><file name="switcher.min.js" server="ftp.greenwoodcreative.com" local="3545906288" remote="3548942040" Dst="-1" /><file name="tab.js" server="ftp.greenwoodcreative.com" local="3545906288" remote="3548942040" Dst="-1" /><file name="tab.min.js" server="ftp.greenwoodcreative.com" local="3545906288" remote="3548942040" Dst="-1" /><file name="toggle.js" server="ftp.greenwoodcreative.com" local="3545906288" remote="3548942040" Dst="-1" /><file name="toggle.min.js" server="ftp.greenwoodcreative.com" local="3545906288" remote="3548942040" Dst="-1" /><file name="touch.js" server="ftp.greenwoodcreative.com" local="3545906288" remote="3548942040" Dst="-1" /><file name="utility.js" server="ftp.greenwoodcreative.com" local="3545906288" remote="3548942040" Dst="-1" /><file name="touch.min.js" server="ftp.greenwoodcreative.com" local="3545906288" remote="3548942040" Dst="-1" /><file name="utility.min.js" server="ftp.greenwoodcreative.com" local="3545906288" remote="3548942040" Dst="-1" /></dwsync>